{
  "db_name": "PostgreSQL",
  "query": "\n        SELECT \n        id, name, surname, email, avatar, role as \"role: RoleModel\"\n        FROM users\n        WHERE company_id = $1\n        ",
  "describe": {
    "columns": [
      {
        "ordinal": 0,
        "name": "id",
        "type_info": "Uuid"
      },
      {
        "ordinal": 1,
        "name": "name",
        "type_info": "Varchar"
      },
      {
        "ordinal": 2,
        "name": "surname",
        "type_info": "Varchar"
      },
      {
        "ordinal": 3,
        "name": "email",
        "type_info": "Varchar"
      },
      {
        "ordinal": 4,
        "name": "avatar",
        "type_info": "Varchar"
      },
      {
        "ordinal": 5,
        "name": "role: RoleModel",
        "type_info": {
          "Custom": {
            "name": "role",
            "kind": {
              "Enum": [
                "admin",
                "student",
                "guest",
                "verified_guest"
              ]
            }
          }
        }
      }
    ],
    "parameters": {
      "Left": [
        "Uuid"
      ]
    },
    "nullable": [
      false,
      false,
      false,
      false,
      true,
      false
    ]
  },
  "hash": "d6c7f2f3c24d22fac8d8749f97700f7727f750c1b0abb91d7370e3c0e5c8e062"
}
